[
  { "_id" : {"ObjectId":"5d00503e167e993b404279fb"}, "PokemonNumber" : "63", "Name" : "Abra", "Type1" : "Psychic", "Type2" : "", "Total" : "310", "HP" : "25", "Attack" : "20", "Defense" : "15", "SpecialAttack" : "105", "SpecialDefense" : "55", "Speed" : "90", "Generation" : "1", "Legendary" : "False" },
  { "_id" : {"ObjectId":"5d00503e167e993b404279fc"}, "PokemonNumber" : "64", "Name" : "Kadabra", "Type1" : "Psychic", "Type2" : "", "Total" : "400", "HP" : "40", "Attack" : "35", "Defense" : "30", "SpecialAttack" : "120", "SpecialDefense" : "70", "Speed" : "105", "Generation" : "1", "Legendary" : "False" },
  { "_id" : {"ObjectId":"5d00503e167e993b404279fd"}, "PokemonNumber" : "65", "Name" : "Alakazam", "Type1" : "Psychic", "Type2" : "", "Total" : "500", "HP" : "55", "Attack" : "50", "Defense" : "45", "SpecialAttack" : "135", "SpecialDefense" : "95", "Speed" : "120", "Generation" : "1", "Legendary" : "False" },
  { "_id" : {"ObjectId":"5d00503e167e993b404279fe"}, "PokemonNumber" : "65", "Name" : "AlakazamMega Alakazam", "Type1" : "Psychic", "Type2" : "", "Total" : "590", "HP" : "55", "Attack" : "50", "Defense" : "65", "SpecialAttack" : "175", "SpecialDefense" : "95", "Speed" : "150", "Generation" : "1", "Legendary" : "False" },
  { "_id" : {"ObjectId":"5d00503e167e993b40427a1f"}, "PokemonNumber" : "96", "Name" : "Drowzee", "Type1" : "Psychic", "Type2" : "", "Total" : "328", "HP" : "60", "Attack" : "48", "Defense" : "45", "SpecialAttack" : "43", "SpecialDefense" : "90", "Speed" : "42", "Generation" : "1", "Legendary" : "False" },
  { "_id" : {"ObjectId":"5d00503e167e993b40427a20"}, "PokemonNumber" : "97", "Name" : "Hypno", "Type1" : "Psychic", "Type2" : "", "Total" : "483", "HP" : "85", "Attack" : "73", "Defense" : "70", "SpecialAttack" : "73", "SpecialDefense" : "115", "Speed" : "67", "Generation" : "1", "Legendary" : "False" },
  { "_id" : {"ObjectId":"5d00503e167e993b40427a3a"}, "PokemonNumber" : "122", "Name" : "Mr. Mime", "Type1" : "Psychic", "Type2" : "Fairy", "Total" : "460", "HP" : "40", "Attack" : "45", "Defense" : "65", "SpecialAttack" : "100", "SpecialDefense" : "120", "Speed" : "90", "Generation" : "1", "Legendary" : "False" },
  { "_id" : {"ObjectId":"5d00503e167e993b40427a59"}, "PokemonNumber" : "150", "Name" : "Mewtwo", "Type1" : "Psychic", "Type2" : "", "Total" : "680", "HP" : "106", "Attack" : "110", "Defense" : "90", "SpecialAttack" : "154", "SpecialDefense" : "90", "Speed" : "130", "Generation" : "1", "Legendary" : "False" },
  { "_id" : {"ObjectId":"5d00503e167e993b40427a5a"}, "PokemonNumber" : "150", "Name" : "MewtwoMega Mewtwo X", "Type1" : "Psychic", "Type2" : "Fighting", "Total" : "780", "HP" : "106", "Attack" : "190", "Defense" : "100", "SpecialAttack" : "154", "SpecialDefense" : "100", "Speed" : "130", "Generation" : "1", "Legendary" : "False" },
  { "_id" : {"ObjectId":"5d00503e167e993b40427a5b"}, "PokemonNumber" : "150", "Name" : "MewtwoMega Mewtwo Y", "Type1" : "Psychic", "Type2" : "", "Total" : "780", "HP" : "106", "Attack" : "150", "Defense" : "70", "SpecialAttack" : "194", "SpecialDefense" : "120", "Speed" : "140", "Generation" : "1", "Legendary" : "False" },
  { "_id" : {"ObjectId":"5d00503e167e993b40427a5c"}, "PokemonNumber" : "151", "Name" : "Mew", "Type1" : "Psychic", "Type2" : "", "Total" : "600", "HP" : "100", "Attack" : "100", "Defense" : "100", "SpecialAttack" : "100", "SpecialDefense" : "100", "Speed" : "100", "Generation" : "1", "Legendary" : "False" },
  { "_id" : {"ObjectId":"5d00503e167e993b40427a76"}, "PokemonNumber" : "177", "Name" : "Natu", "Type1" : "Psychic", "Type2" : "Flying", "Total" : "320", "HP" : "40", "Attack" : "50", "Defense" : "45", "SpecialAttack" : "70", "SpecialDefense" : "45", "Speed" : "70", "Generation" : "2", "Legendary" : "False" },
  { "_id" : {"ObjectId":"5d00503e167e993b40427a77"}, "PokemonNumber" : "178", "Name" : "Xatu", "Type1" : "Psychic", "Type2" : "Flying", "Total" : "470", "HP" : "65", "Attack" : "75", "Defense" : "70", "SpecialAttack" : "95", "SpecialDefense" : "70", "Speed" : "95", "Generation" : "2", "Legendary" : "False" },
  { "_id" : {"ObjectId":"5d00503e167e993b40427a8a"}, "PokemonNumber" : "196", "Name" : "Espeon", "Type1" : "Psychic", "Type2" : "", "Total" : "525", "HP" : "65", "Attack" : "65", "Defense" : "60", "SpecialAttack" : "130", "SpecialDefense" : "95", "Speed" : "110", "Generation" : "2", "Legendary" : "False" },
  { "_id" : {"ObjectId":"5d00503e167e993b40427a8f"}, "PokemonNumber" : "201", "Name" : "Unown", "Type1" : "Psychic", "Type2" : "", "Total" : "336", "HP" : "48", "Attack" : "72", "Defense" : "48", "SpecialAttack" : "72", "SpecialDefense" : "48", "Speed" : "48", "Generation" : "2", "Legendary" : "False" },
  { "_id" : {"ObjectId":"5d00503e167e993b40427a90"}, "PokemonNumber" : "202", "Name" : "Wobbuffet", "Type1" : "Psychic", "Type2" : "", "Total" : "405", "HP" : "190", "Attack" : "33", "Defense" : "58", "SpecialAttack" : "33", "SpecialDefense" : "58", "Speed" : "33", "Generation" : "2", "Legendary" : "False" },
  { "_id" : {"ObjectId":"5d00503e167e993b40427ac4"}, "PokemonNumber" : "249", "Name" : "Lugia", "Type1" : "Psychic", "Type2" : "Flying", "Total" : "680", "HP" : "106", "Attack" : "90", "Defense" : "130", "SpecialAttack" : "90", "SpecialDefense" : "154", "Speed" : "110", "Generation" : "2", "Legendary" : "False" },
  { "_id" : {"ObjectId":"5d00503e167e993b40427ac6"}, "PokemonNumber" : "251", "Name" : "Celebi", "Type1" : "Psychic", "Type2" : "Grass", "Total" : "600", "HP" : "100", "Attack" : "100", "Defense" : "100", "SpecialAttack" : "100", "SpecialDefense" : "100", "Speed" : "100", "Generation" : "2", "Legendary" : "False" },
  { "_id" : {"ObjectId":"5d00503e167e993b40427ae6"}, "PokemonNumber" : "280", "Name" : "Ralts", "Type1" : "Psychic", "Type2" : "Fairy", "Total" : "198", "HP" : "28", "Attack" : "25", "Defense" : "25", "SpecialAttack" : "45", "SpecialDefense" : "35", "Speed" : "40", "Generation" : "3", "Legendary" : "False" },
  { "_id" : {"ObjectId":"5d00503e167e993b40427ae7"}, "PokemonNumber" : "281", "Name" : "Kirlia", "Type1" : "Psychic", "Type2" : "Fairy", "Total" : "278", "HP" : "38", "Attack" : "35", "Defense" : "35", "SpecialAttack" : "65", "SpecialDefense" : "55", "Speed" : "50", "Generation" : "3", "Legendary" : "False" }
]
